abru/__init__.py
abru/speak.py
abru/take_command.py
abru/wish.py
Abrez-0.0.2.dist-info/LICENSE
Abrez-0.0.2.dist-info/METADATA
Abrez-0.0.2.dist-info/WHEEL
Abrez-0.0.2.dist-info/top_level.txt
Abrez-0.0.2.dist-info/RECORD
